medha_one_access/__init__.py
medha_one_access/py.typed
medha_one_access/api/__init__.py
medha_one_access/api/app.py
medha_one_access/api/dependencies.py
medha_one_access/api/mount.py
medha_one_access/api/routers/__init__.py
medha_one_access/api/routers/access_check.py
medha_one_access/api/routers/access_rules.py
medha_one_access/api/routers/access_summary.py
medha_one_access/api/routers/artifacts.py
medha_one_access/api/routers/data_io.py
medha_one_access/api/routers/expressions.py
medha_one_access/api/routers/reporting.py
medha_one_access/api/routers/resourcegroups.py
medha_one_access/api/routers/usergroups.py
medha_one_access/api/routers/users.py
medha_one_access/cli/__init__.py
medha_one_access/cli/__main__.py
medha_one_access/cli/main.py
medha_one_access/core/__init__.py
medha_one_access/core/background_tasks.py
medha_one_access/core/base.py
medha_one_access/core/cache.py
medha_one_access/core/compatibility.py
medha_one_access/core/config.py
medha_one_access/core/constraints.py
medha_one_access/core/controller.py
medha_one_access/core/database.py
medha_one_access/core/exceptions.py
medha_one_access/core/expressions.py
medha_one_access/core/models.py
medha_one_access/core/resolver.py
medha_one_access/core/schemas.py
medha_one_access/migrations/alembic.ini
medha_one_access/migrations/env.py
medha_one_access/migrations/script.py.mako
medha_one_access/migrations/versions/001_initial_schema.py
medha_one_access/migrations/versions/002_add_application_to_access_summaries.py
medha_one_access-0.3.3.dist-info/licenses/LICENSE
medha_one_access-0.3.3.dist-info/METADATA
medha_one_access-0.3.3.dist-info/WHEEL
medha_one_access-0.3.3.dist-info/entry_points.txt
medha_one_access-0.3.3.dist-info/top_level.txt
medha_one_access-0.3.3.dist-info/RECORD
