Metadata-Version: 2.4
Name: medha-one-access
Version: 0.3.3
Summary: Enterprise access control system with BODMAS resolution
Home-page: https://github.com/medhaone-analytics/medha-one-access
Author: MedhaOne Analytics
Author-email: MedhaOne Analytics <contactmedhaanalytics@gmail.com>
Maintainer-email: MedhaOne Analytics <contactmedhaanalytics@gmail.com>
License: MIT
Project-URL: Homepage, https://github.com/medhaone-analytics/medha-one-access
Project-URL: Documentation, https://medha-one-access.readthedocs.io/
Project-URL: Repository, https://github.com/medhaone-analytics/medha-one-access
Project-URL: Bug Reports, https://github.com/medhaone-analytics/medha-one-access/issues
Project-URL: Changelog, https://github.com/medhaone-analytics/medha-one-access/blob/main/CHANGELOG.md
Keywords: access-control,authorization,permissions,rbac,abac,bodmas,expressions,security,fastapi,sqlalchemy
Classifier: Development Status :: 4 - Beta
Classifier: Intended Audience :: Developers
Classifier: License :: OSI Approved :: MIT License
Classifier: Operating System :: OS Independent
Classifier: Programming Language :: Python :: 3
Classifier: Programming Language :: Python :: 3.8
Classifier: Programming Language :: Python :: 3.9
Classifier: Programming Language :: Python :: 3.10
Classifier: Programming Language :: Python :: 3.11
Classifier: Programming Language :: Python :: 3.12
Classifier: Topic :: Security
Classifier: Topic :: Software Development :: Libraries :: Python Modules
Classifier: Topic :: System :: Systems Administration :: Authentication/Directory
Classifier: Typing :: Typed
Requires-Python: >=3.8
License-File: LICENSE
Requires-Dist: sqlalchemy[asyncio]>=2.0.0
Requires-Dist: pydantic
Requires-Dist: asyncpg>=0.28.0
Requires-Dist: aiosqlite>=0.19.0
Requires-Dist: cryptography
Requires-Dist: alembic
Requires-Dist: python-dateutil
Requires-Dist: aiofiles>=23.0.0
Requires-Dist: asyncio-throttle>=1.0.2
Provides-Extra: api
Requires-Dist: fastapi; extra == "api"
Requires-Dist: uvicorn; extra == "api"
Requires-Dist: python-multipart; extra == "api"
Provides-Extra: cli
Requires-Dist: click; extra == "cli"
Requires-Dist: rich; extra == "cli"
Requires-Dist: typer; extra == "cli"
Provides-Extra: dev
Requires-Dist: black; extra == "dev"
Requires-Dist: flake8; extra == "dev"
Requires-Dist: mypy; extra == "dev"
Requires-Dist: sphinx; extra == "dev"
Requires-Dist: sphinx-rtd-theme; extra == "dev"
Requires-Dist: pytest-asyncio>=0.21.0; extra == "dev"
Requires-Dist: aioresponses>=0.7.4; extra == "dev"
Provides-Extra: all
Requires-Dist: medha-one-access[api,cli,dev]; extra == "all"
Dynamic: author
Dynamic: home-page
Dynamic: license-file
Dynamic: requires-python
